clientapi_atrocore/__init__.py
clientapi_atrocore/api_client.py
clientapi_atrocore/api_response.py
clientapi_atrocore/configuration.py
clientapi_atrocore/exceptions.py
clientapi_atrocore/py.typed
clientapi_atrocore/rest.py
clientapi_atrocore/api/__init__.py
clientapi_atrocore/api/account_api.py
clientapi_atrocore/api/app_api.py
clientapi_atrocore/api/asset_api.py
clientapi_atrocore/api/asset_category_api.py
clientapi_atrocore/api/asset_metadata_api.py
clientapi_atrocore/api/asset_type_api.py
clientapi_atrocore/api/associated_product_api.py
clientapi_atrocore/api/association_api.py
clientapi_atrocore/api/attachment_api.py
clientapi_atrocore/api/attribute_api.py
clientapi_atrocore/api/attribute_group_api.py
clientapi_atrocore/api/attribute_tab_api.py
clientapi_atrocore/api/auth_log_record_api.py
clientapi_atrocore/api/auth_token_api.py
clientapi_atrocore/api/brand_api.py
clientapi_atrocore/api/catalog_api.py
clientapi_atrocore/api/category_api.py
clientapi_atrocore/api/category_asset_api.py
clientapi_atrocore/api/channel_api.py
clientapi_atrocore/api/classification_api.py
clientapi_atrocore/api/classification_attribute_api.py
clientapi_atrocore/api/composer_api.py
clientapi_atrocore/api/connection_api.py
clientapi_atrocore/api/content_api.py
clientapi_atrocore/api/content_group_api.py
clientapi_atrocore/api/dashlet_api.py
clientapi_atrocore/api/export_configurator_item_api.py
clientapi_atrocore/api/export_feed_api.py
clientapi_atrocore/api/export_job_api.py
clientapi_atrocore/api/extensible_enum_api.py
clientapi_atrocore/api/extensible_enum_option_api.py
clientapi_atrocore/api/import_configurator_item_api.py
clientapi_atrocore/api/import_feed_api.py
clientapi_atrocore/api/import_job_api.py
clientapi_atrocore/api/import_job_log_api.py
clientapi_atrocore/api/job_api.py
clientapi_atrocore/api/library_api.py
clientapi_atrocore/api/locale_api.py
clientapi_atrocore/api/mass_actions_api.py
clientapi_atrocore/api/measure_api.py
clientapi_atrocore/api/note_api.py
clientapi_atrocore-1.0.0.dist-info/LICENSE
clientapi_atrocore-1.0.0.dist-info/METADATA
clientapi_atrocore-1.0.0.dist-info/WHEEL
clientapi_atrocore-1.0.0.dist-info/top_level.txt
clientapi_atrocore-1.0.0.dist-info/RECORD
