Metadata-Version: 2.1
Name: clientapi-atrocore
Version: 1.0.0
Summary: AtroCore REST API documentation
Home-page: https://github.com/client-api/atrocore-python
Author: OpenAPI Generator community
Author-email: team@openapitools.org
Keywords: OpenAPI,OpenAPI-Generator,AtroCore REST API documentation
License-File: LICENSE
Requires-Dist: urllib3 <2.1.0,>=1.25.3
Requires-Dist: python-dateutil
Requires-Dist: pydantic <2,>=1.10.5
Requires-Dist: aenum
